django_admin_lazy_count/__init__.py
django_admin_lazy_count/apps.py
django_admin_lazy_count/main.py
django_admin_lazy_count/migrations/__init__.py
django_admin_lazy_count/templates/django_admin_lazy_count/lazy_pagination.html
django_lazy_admin_pagination-1.0.2.dist-info/METADATA
django_lazy_admin_pagination-1.0.2.dist-info/WHEEL
django_lazy_admin_pagination-1.0.2.dist-info/top_level.txt
django_lazy_admin_pagination-1.0.2.dist-info/RECORD
