Metadata-Version: 2.1
Name: django-lazy-admin-pagination
Version: 1.0.2
Summary: A Django package for lazy-loading pagination in the admin interface.
Home-page: https://github.com/anish5256/django-lazy-admin-pagination
Author: Anish Kumar
Author-email: anish5256@gmail.com
Classifier: Framework :: Django
Classifier: Programming Language :: Python :: 3
Classifier: License :: OSI Approved :: MIT License
Classifier: Operating System :: OS Independent
Requires-Python: >=3.6
Requires-Dist: Django>=3.2
